CHANGELOG.md
COPYING
README.md
bin/__init__.py
bin/enigma.py
pyenigma/__init__.py
pyenigma/enigma.py
pyenigma/rotor.py
pyenigma-0.4.2.dist-info/COPYING
pyenigma-0.4.2.dist-info/METADATA
pyenigma-0.4.2.dist-info/WHEEL
pyenigma-0.4.2.dist-info/entry_points.txt
pyenigma-0.4.2.dist-info/RECORD
