Metadata-Version: 2.1
Name: pyenigma
Version: 0.4.2
Summary: Python Enigma cypher machine simulator.
Home-page: https://sr.ht/~cedric/pyenigma
License: GPL-3.0-or-later
Keywords: cryptography,security,enigma
Author: Cédric Bonhomme
Author-email: cedric@cedricbonhomme.org
Requires-Python: >=3.10,<4.0
Classifier: Development Status :: 5 - Production/Stable
Classifier: Environment :: Console
Classifier: Intended Audience :: Developers
Classifier: Intended Audience :: Science/Research
Classifier: License :: OSI Approved :: GNU General Public License v3 or later (GPLv3+)
Classifier: Operating System :: OS Independent
Classifier: Programming Language :: Python :: 3
Classifier: Programming Language :: Python :: 3.10
Classifier: Programming Language :: Python :: 3.11
Classifier: Programming Language :: Python :: 3.12
Classifier: Topic :: Security
Project-URL: Repository, https://git.sr.ht/~cedric/pyenigma
